{"nodes": [{"id": "users_ea_enel_documents_00_my_librefolio_librefolio_devwiki_corpus_backend_api_v1_assets_py", "label": "assets.py", "file_type": "code", "source_file": "backend/api/v1/assets.py", "source_location": "L1"}, {"id": "v1_assets_create_assets_bulk", "label": "create_assets_bulk()", "file_type": "code", "source_file": "backend/api/v1/assets.py", "source_location": "L84"}, {"id": "faassetcreateitem", "label": "FAAssetCreateItem", "file_type": "code", "source_file": "backend/api/v1/assets.py", "source_location": "L84"}, {"id": "asyncsession", "label": "AsyncSession", "file_type": "code", "source_file": "backend/api/v1/assets.py", "source_location": "L84"}, {"id": "user", "label": "User", "file_type": "code", "source_file": "backend/api/v1/assets.py", "source_location": "L84"}, {"id": "v1_assets_patch_assets_bulk", "label": "patch_assets_bulk()", "file_type": "code", "source_file": "backend/api/v1/assets.py", "source_location": "L135"}, {"id": "faassetpatchitem", "label": "FAAssetPatchItem", "file_type": "code", "source_file": "backend/api/v1/assets.py", "source_location": "L135"}, {"id": "v1_assets_get_all_assets", "label": "get_all_assets()", "file_type": "code", "source_file": "backend/api/v1/assets.py", "source_location": "L201"}, {"id": "v1_assets_list_assets", "label": "list_assets()", "file_type": "code", "source_file": "backend/api/v1/assets.py", "source_location": "L221"}, {"id": "assettype", "label": "AssetType", "file_type": "code", "source_file": "backend/api/v1/assets.py", "source_location": "L221"}, {"id": "v1_assets_delete_assets_bulk", "label": "delete_assets_bulk()", "file_type": "code", "source_file": "backend/api/v1/assets.py", "source_location": "L289"}, {"id": "v1_assets_list_providers", "label": "list_providers()", "file_type": "code", "source_file": "backend/api/v1/assets.py", "source_location": "L341"}, {"id": "v1_assets_search_assets_via_providers", "label": "search_assets_via_providers()", "file_type": "code", "source_file": "backend/api/v1/assets.py", "source_location": "L392"}, {"id": "v1_assets_search_assets_stream", "label": "search_assets_stream()", "file_type": "code", "source_file": "backend/api/v1/assets.py", "source_location": "L451"}, {"id": "v1_assets_probe_provider_config", "label": "probe_provider_config()", "file_type": "code", "source_file": "backend/api/v1/assets.py", "source_location": "L484"}, {"id": "faproviderproberequest", "label": "FAProviderProbeRequest", "file_type": "code", "source_file": "backend/api/v1/assets.py", "source_location": "L484"}, {"id": "v1_assets_assign_providers_bulk", "label": "assign_providers_bulk()", "file_type": "code", "source_file": "backend/api/v1/assets.py", "source_location": "L516"}, {"id": "faproviderassignmentitem", "label": "FAProviderAssignmentItem", "file_type": "code", "source_file": "backend/api/v1/assets.py", "source_location": "L516"}, {"id": "v1_assets_remove_providers_bulk", "label": "remove_providers_bulk()", "file_type": "code", "source_file": "backend/api/v1/assets.py", "source_location": "L532"}, {"id": "v1_assets_get_provider_assignments", "label": "get_provider_assignments()", "file_type": "code", "source_file": "backend/api/v1/assets.py", "source_location": "L546"}, {"id": "v1_assets_upsert_prices_bulk", "label": "upsert_prices_bulk()", "file_type": "code", "source_file": "backend/api/v1/assets.py", "source_location": "L616"}, {"id": "faupsert", "label": "FAUpsert", "file_type": "code", "source_file": "backend/api/v1/assets.py", "source_location": "L616"}, {"id": "v1_assets_delete_prices_bulk", "label": "delete_prices_bulk()", "file_type": "code", "source_file": "backend/api/v1/assets.py", "source_location": "L646"}, {"id": "faassetdelete", "label": "FAAssetDelete", "file_type": "code", "source_file": "backend/api/v1/assets.py", "source_location": "L646"}, {"id": "v1_assets_query_prices_bulk", "label": "query_prices_bulk()", "file_type": "code", "source_file": "backend/api/v1/assets.py", "source_location": "L672"}, {"id": "fapricequeryitem", "label": "FAPriceQueryItem", "file_type": "code", "source_file": "backend/api/v1/assets.py", "source_location": "L672"}, {"id": "v1_assets_get_current_prices_bulk", "label": "get_current_prices_bulk()", "file_type": "code", "source_file": "backend/api/v1/assets.py", "source_location": "L692"}, {"id": "v1_assets_read_assets_bulk", "label": "read_assets_bulk()", "file_type": "code", "source_file": "backend/api/v1/assets.py", "source_location": "L737"}, {"id": "v1_assets_sync_prices_bulk", "label": "sync_prices_bulk()", "file_type": "code", "source_file": "backend/api/v1/assets.py", "source_location": "L865"}, {"id": "farefreshitem", "label": "FARefreshItem", "file_type": "code", "source_file": "backend/api/v1/assets.py", "source_location": "L865"}, {"id": "v1_assets_refresh_assets_from_provider", "label": "refresh_assets_from_provider()", "file_type": "code", "source_file": "backend/api/v1/assets.py", "source_location": "L879"}, {"id": "v1_assets_upsert_events_bulk", "label": "upsert_events_bulk()", "file_type": "code", "source_file": "backend/api/v1/assets.py", "source_location": "L954"}, {"id": "faeventupsert", "label": "FAEventUpsert", "file_type": "code", "source_file": "backend/api/v1/assets.py", "source_location": "L954"}, {"id": "v1_assets_delete_events_bulk", "label": "delete_events_bulk()", "file_type": "code", "source_file": "backend/api/v1/assets.py", "source_location": "L985"}, {"id": "v1_assets_query_events_bulk", "label": "query_events_bulk()", "file_type": "code", "source_file": "backend/api/v1/assets.py", "source_location": "L1010"}, {"id": "faeventqueryitem", "label": "FAEventQueryItem", "file_type": "code", "source_file": "backend/api/v1/assets.py", "source_location": "L1010"}, {"id": "v1_assets_get_events_by_ids", "label": "get_events_by_ids()", "file_type": "code", "source_file": "backend/api/v1/assets.py", "source_location": "L1028"}, {"id": "v1_assets_market_data_summary", "label": "market_data_summary()", "file_type": "code", "source_file": "backend/api/v1/assets.py", "source_location": "L1082"}, {"id": "v1_assets_wipe_market_data", "label": "wipe_market_data()", "file_type": "code", "source_file": "backend/api/v1/assets.py", "source_location": "L1105"}, {"id": "v1_assets_rationale_1", "label": "Asset Provider API endpoints. Handles provider assignment, price management, and", "file_type": "rationale", "source_file": "backend/api/v1/assets.py", "source_location": "L1"}, {"id": "v1_assets_rationale_89", "label": "Create multiple assets in bulk (partial success allowed).      Creates asset rec", "file_type": "rationale", "source_file": "backend/api/v1/assets.py", "source_location": "L89"}, {"id": "v1_assets_rationale_140", "label": "Update multiple assets in bulk (partial success allowed).      **Merge Logic**:", "file_type": "rationale", "source_file": "backend/api/v1/assets.py", "source_location": "L140"}, {"id": "v1_assets_rationale_202", "label": "Get all active assets without filters.      Simple endpoint for frontend to load", "file_type": "rationale", "source_file": "backend/api/v1/assets.py", "source_location": "L202"}, {"id": "v1_assets_rationale_237", "label": "List all assets with optional filters - enhanced for BRIM asset matching.      *", "file_type": "rationale", "source_file": "backend/api/v1/assets.py", "source_location": "L237"}, {"id": "v1_assets_rationale_294", "label": "Delete multiple assets in bulk (partial success allowed).      **Warning**: This", "file_type": "rationale", "source_file": "backend/api/v1/assets.py", "source_location": "L294"}, {"id": "v1_assets_rationale_345", "label": "List all available asset pricing providers.      Optionally filter by provider c", "file_type": "rationale", "source_file": "backend/api/v1/assets.py", "source_location": "L345"}, {"id": "v1_assets_rationale_397", "label": "Search for assets across one or more providers in parallel.      Queries the spe", "file_type": "rationale", "source_file": "backend/api/v1/assets.py", "source_location": "L397"}, {"id": "v1_assets_rationale_456", "label": "Stream search results via Server-Sent Events (SSE).      Each provider returns r", "file_type": "rationale", "source_file": "backend/api/v1/assets.py", "source_location": "L456"}, {"id": "v1_assets_rationale_521", "label": "Bulk assign providers to assets (PRIMARY bulk endpoint).", "file_type": "rationale", "source_file": "backend/api/v1/assets.py", "source_location": "L521"}, {"id": "v1_assets_rationale_537", "label": "Bulk remove provider assignments (PRIMARY bulk endpoint).", "file_type": "rationale", "source_file": "backend/api/v1/assets.py", "source_location": "L537"}, {"id": "v1_assets_rationale_551", "label": "Get provider assignments for multiple assets.      Returns identifier, identifie", "file_type": "rationale", "source_file": "backend/api/v1/assets.py", "source_location": "L551"}, {"id": "v1_assets_rationale_621", "label": "Bulk upsert prices manually (PRIMARY bulk endpoint).", "file_type": "rationale", "source_file": "backend/api/v1/assets.py", "source_location": "L621"}, {"id": "v1_assets_rationale_651", "label": "Bulk delete price ranges (PRIMARY bulk endpoint).", "file_type": "rationale", "source_file": "backend/api/v1/assets.py", "source_location": "L651"}, {"id": "v1_assets_rationale_677", "label": "Bulk query prices for multiple assets.      Reads from DB only (no provider dele", "file_type": "rationale", "source_file": "backend/api/v1/assets.py", "source_location": "L677"}, {"id": "v1_assets_rationale_697", "label": "Bulk fetch current/live prices for multiple assets.      For each asset:     1.", "file_type": "rationale", "source_file": "backend/api/v1/assets.py", "source_location": "L697"}, {"id": "v1_assets_rationale_742", "label": "Bulk read assets with classification metadata (preserves request order).      Fe", "file_type": "rationale", "source_file": "backend/api/v1/assets.py", "source_location": "L742"}, {"id": "v1_assets_rationale_870", "label": "Bulk sync prices via providers (PRIMARY bulk endpoint).", "file_type": "rationale", "source_file": "backend/api/v1/assets.py", "source_location": "L870"}, {"id": "v1_assets_rationale_884", "label": "Refresh asset data from assigned providers (bulk operation).      **EXPLICIT REF", "file_type": "rationale", "source_file": "backend/api/v1/assets.py", "source_location": "L884"}, {"id": "v1_assets_rationale_959", "label": "Bulk upsert manual events (provider_assignment_id = NULL).      Creates or updat", "file_type": "rationale", "source_file": "backend/api/v1/assets.py", "source_location": "L959"}, {"id": "v1_assets_rationale_990", "label": "Bulk delete asset events with RESTRICT-aware response.      For each id, returns", "file_type": "rationale", "source_file": "backend/api/v1/assets.py", "source_location": "L990"}, {"id": "v1_assets_rationale_1015", "label": "Bulk query events for multiple assets.      Returns events with id and is_auto f", "file_type": "rationale", "source_file": "backend/api/v1/assets.py", "source_location": "L1015"}, {"id": "v1_assets_rationale_1033", "label": "Fetch specific events by their IDs.      Returns the same shape as POST /events/", "file_type": "rationale", "source_file": "backend/api/v1/assets.py", "source_location": "L1033"}, {"id": "v1_assets_rationale_1087", "label": "Return market-data counters for an asset (dry-run summary).      Used by the cur", "file_type": "rationale", "source_file": "backend/api/v1/assets.py", "source_location": "L1087"}, {"id": "v1_assets_rationale_1110", "label": "Wipe all market data (prices + events) and disconnect linked transactions.", "file_type": "rationale", "source_file": "backend/api/v1/assets.py", "source_location": "L1110"}], "edges": [{"source": "users_ea_enel_documents_00_my_librefolio_librefolio_devwiki_corpus_backend_api_v1_assets_py", "target": "json", "relation": "imports", "context": "import", "confidence": "EXTRACTED", "source_file": "backend/api/v1/assets.py", "source_location": "L6", "weight": 1.0}, {"source": "users_ea_enel_documents_00_my_librefolio_librefolio_devwiki_corpus_backend_api_v1_assets_py", "target": "typing", "relation": "imports_from", "context": "import", "confidence": "EXTRACTED", "source_file": "backend/api/v1/assets.py", "source_location": "L7", "weight": 1.0}, {"source": "users_ea_enel_documents_00_my_librefolio_librefolio_devwiki_corpus_backend_api_v1_assets_py", "target": "fastapi", "relation": "imports_from", "context": "import", "confidence": "EXTRACTED", "source_file": "backend/api/v1/assets.py", "source_location": "L9", "weight": 1.0}, {"source": "users_ea_enel_documents_00_my_librefolio_librefolio_devwiki_corpus_backend_api_v1_assets_py", "target": "sqlalchemy", "relation": "imports_from", "context": "import", "confidence": "EXTRACTED", "source_file": "backend/api/v1/assets.py", "source_location": "L10", "weight": 1.0}, {"source": "users_ea_enel_documents_00_my_librefolio_librefolio_devwiki_corpus_backend_api_v1_assets_py", "target": "sqlalchemy_ext_asyncio", "relation": "imports_from", "context": "import", "confidence": "EXTRACTED", "source_file": "backend/api/v1/assets.py", "source_location": "L11", "weight": 1.0}, {"source": "users_ea_enel_documents_00_my_librefolio_librefolio_devwiki_corpus_backend_api_v1_assets_py", "target": "starlette_responses", "relation": "imports_from", "context": "import", "confidence": "EXTRACTED", "source_file": "backend/api/v1/assets.py", "source_location": "L12", "weight": 1.0}, {"source": "users_ea_enel_documents_00_my_librefolio_librefolio_devwiki_corpus_backend_api_v1_assets_py", "target": "backend_app_api_v1_auth", "relation": "imports_from", "context": "import", "confidence": "EXTRACTED", "source_file": "backend/api/v1/assets.py", "source_location": "L14", "weight": 1.0}, {"source": "users_ea_enel_documents_00_my_librefolio_librefolio_devwiki_corpus_backend_api_v1_assets_py", "target": "backend_app_db_models", "relation": "imports_from", "context": "import", "confidence": "EXTRACTED", "source_file": "backend/api/v1/assets.py", "source_location": "L15", "weight": 1.0}, {"source": "users_ea_enel_documents_00_my_librefolio_librefolio_devwiki_corpus_backend_api_v1_assets_py", "target": "backend_app_db_session", "relation": "imports_from", "context": "import", "confidence": "EXTRACTED", "source_file": "backend/api/v1/assets.py", "source_location": "L16", "weight": 1.0}, {"source": "users_ea_enel_documents_00_my_librefolio_librefolio_devwiki_corpus_backend_api_v1_assets_py", "target": "backend_app_logging_config", "relation": "imports_from", "context": "import", "confidence": "EXTRACTED", "source_file": "backend/api/v1/assets.py", "source_location": "L17", "weight": 1.0}, {"source": "users_ea_enel_documents_00_my_librefolio_librefolio_devwiki_corpus_backend_api_v1_assets_py", "target": "backend_app_schemas_assets", "relation": "imports_from", "context": "import", "confidence": "EXTRACTED", "source_file": "backend/api/v1/assets.py", "source_location": "L18", "weight": 1.0}, {"source": "users_ea_enel_documents_00_my_librefolio_librefolio_devwiki_corpus_backend_api_v1_assets_py", "target": "backend_app_schemas_prices", "relation": "imports_from", "context": "import", "confidence": "EXTRACTED", "source_file": "backend/api/v1/assets.py", "source_location": "L32", "weight": 1.0}, {"source": "users_ea_enel_documents_00_my_librefolio_librefolio_devwiki_corpus_backend_api_v1_assets_py", "target": "backend_app_schemas_provider", "relation": "imports_from", "context": "import", "confidence": "EXTRACTED", "source_file": "backend/api/v1/assets.py", "source_location": "L49", "weight": 1.0}, {"source": "users_ea_enel_documents_00_my_librefolio_librefolio_devwiki_corpus_backend_api_v1_assets_py", "target": "backend_app_schemas_refresh", "relation": "imports_from", "context": "import", "confidence": "EXTRACTED", "source_file": "backend/api/v1/assets.py", "source_location": "L61", "weight": 1.0}, {"source": "users_ea_enel_documents_00_my_librefolio_librefolio_devwiki_corpus_backend_api_v1_assets_py", "target": "backend_app_services_asset_source", "relation": "imports_from", "context": "import", "confidence": "EXTRACTED", "source_file": "backend/api/v1/assets.py", "source_location": "L62", "weight": 1.0}, {"source": "users_ea_enel_documents_00_my_librefolio_librefolio_devwiki_corpus_backend_api_v1_assets_py", "target": "backend_app_services_provider_registry", "relation": "imports_from", "context": "import", "confidence": "EXTRACTED", "source_file": "backend/api/v1/assets.py", "source_location": "L68", "weight": 1.0}, {"source": "users_ea_enel_documents_00_my_librefolio_librefolio_devwiki_corpus_backend_api_v1_assets_py", "target": "v1_assets_create_assets_bulk", "relation": "contains", "confidence": "EXTRACTED", "source_file": "backend/api/v1/assets.py", "source_location": "L84", "weight": 1.0}, {"source": "v1_assets_create_assets_bulk", "target": "faassetcreateitem", "relation": "references", "context": "generic_arg", "confidence": "EXTRACTED", "source_file": "backend/api/v1/assets.py", "source_location": "L84", "weight": 1.0}, {"source": "v1_assets_create_assets_bulk", "target": "asyncsession", "relation": "references", "context": "parameter_type", "confidence": "EXTRACTED", "source_file": "backend/api/v1/assets.py", "source_location": "L84", "weight": 1.0}, {"source": "v1_assets_create_assets_bulk", "target": "user", "relation": "references", "context": "parameter_type", "confidence": "EXTRACTED", "source_file": "backend/api/v1/assets.py", "source_location": "L84", "weight": 1.0}, {"source": "users_ea_enel_documents_00_my_librefolio_librefolio_devwiki_corpus_backend_api_v1_assets_py", "target": "v1_assets_patch_assets_bulk", "relation": "contains", "confidence": "EXTRACTED", "source_file": "backend/api/v1/assets.py", "source_location": "L135", "weight": 1.0}, {"source": "v1_assets_patch_assets_bulk", "target": "faassetpatchitem", "relation": "references", "context": "generic_arg", "confidence": "EXTRACTED", "source_file": "backend/api/v1/assets.py", "source_location": "L135", "weight": 1.0}, {"source": "v1_assets_patch_assets_bulk", "target": "asyncsession", "relation": "references", "context": "parameter_type", "confidence": "EXTRACTED", "source_file": "backend/api/v1/assets.py", "source_location": "L135", "weight": 1.0}, {"source": "v1_assets_patch_assets_bulk", "target": "user", "relation": "references", "context": "parameter_type", "confidence": "EXTRACTED", "source_file": "backend/api/v1/assets.py", "source_location": "L135", "weight": 1.0}, {"source": "users_ea_enel_documents_00_my_librefolio_librefolio_devwiki_corpus_backend_api_v1_assets_py", "target": "v1_assets_get_all_assets", "relation": "contains", "confidence": "EXTRACTED", "source_file": "backend/api/v1/assets.py", "source_location": "L201", "weight": 1.0}, {"source": "v1_assets_get_all_assets", "target": "asyncsession", "relation": "references", "context": "parameter_type", "confidence": "EXTRACTED", "source_file": "backend/api/v1/assets.py", "source_location": "L201", "weight": 1.0}, {"source": "v1_assets_get_all_assets", "target": "user", "relation": "references", "context": "parameter_type", "confidence": "EXTRACTED", "source_file": "backend/api/v1/assets.py", "source_location": "L201", "weight": 1.0}, {"source": "users_ea_enel_documents_00_my_librefolio_librefolio_devwiki_corpus_backend_api_v1_assets_py", "target": "v1_assets_list_assets", "relation": "contains", "confidence": "EXTRACTED", "source_file": "backend/api/v1/assets.py", "source_location": "L221", "weight": 1.0}, {"source": "v1_assets_list_assets", "target": "assettype", "relation": "references", "context": "generic_arg", "confidence": "EXTRACTED", "source_file": "backend/api/v1/assets.py", "source_location": "L221", "weight": 1.0}, {"source": "v1_assets_list_assets", "target": "asyncsession", "relation": "references", "context": "parameter_type", "confidence": "EXTRACTED", "source_file": "backend/api/v1/assets.py", "source_location": "L221", "weight": 1.0}, {"source": "v1_assets_list_assets", "target": "user", "relation": "references", "context": "parameter_type", "confidence": "EXTRACTED", "source_file": "backend/api/v1/assets.py", "source_location": "L221", "weight": 1.0}, {"source": "users_ea_enel_documents_00_my_librefolio_librefolio_devwiki_corpus_backend_api_v1_assets_py", "target": "v1_assets_delete_assets_bulk", "relation": "contains", "confidence": "EXTRACTED", "source_file": "backend/api/v1/assets.py", "source_location": "L289", "weight": 1.0}, {"source": "v1_assets_delete_assets_bulk", "target": "asyncsession", "relation": "references", "context": "parameter_type", "confidence": "EXTRACTED", "source_file": "backend/api/v1/assets.py", "source_location": "L289", "weight": 1.0}, {"source": "v1_assets_delete_assets_bulk", "target": "user", "relation": "references", "context": "parameter_type", "confidence": "EXTRACTED", "source_file": "backend/api/v1/assets.py", "source_location": "L289", "weight": 1.0}, {"source": "users_ea_enel_documents_00_my_librefolio_librefolio_devwiki_corpus_backend_api_v1_assets_py", "target": "v1_assets_list_providers", "relation": "contains", "confidence": "EXTRACTED", "source_file": "backend/api/v1/assets.py", "source_location": "L341", "weight": 1.0}, {"source": "v1_assets_list_providers", "target": "user", "relation": "references", "context": "parameter_type", "confidence": "EXTRACTED", "source_file": "backend/api/v1/assets.py", "source_location": "L341", "weight": 1.0}, {"source": "users_ea_enel_documents_00_my_librefolio_librefolio_devwiki_corpus_backend_api_v1_assets_py", "target": "v1_assets_search_assets_via_providers", "relation": "contains", "confidence": "EXTRACTED", "source_file": "backend/api/v1/assets.py", "source_location": "L392", "weight": 1.0}, {"source": "v1_assets_search_assets_via_providers", "target": "user", "relation": "references", "context": "parameter_type", "confidence": "EXTRACTED", "source_file": "backend/api/v1/assets.py", "source_location": "L392", "weight": 1.0}, {"source": "users_ea_enel_documents_00_my_librefolio_librefolio_devwiki_corpus_backend_api_v1_assets_py", "target": "v1_assets_search_assets_stream", "relation": "contains", "confidence": "EXTRACTED", "source_file": "backend/api/v1/assets.py", "source_location": "L451", "weight": 1.0}, {"source": "v1_assets_search_assets_stream", "target": "user", "relation": "references", "context": "parameter_type", "confidence": "EXTRACTED", "source_file": "backend/api/v1/assets.py", "source_location": "L451", "weight": 1.0}, {"source": "users_ea_enel_documents_00_my_librefolio_librefolio_devwiki_corpus_backend_api_v1_assets_py", "target": "v1_assets_probe_provider_config", "relation": "contains", "confidence": "EXTRACTED", "source_file": "backend/api/v1/assets.py", "source_location": "L484", "weight": 1.0}, {"source": "v1_assets_probe_provider_config", "target": "faproviderproberequest", "relation": "references", "context": "parameter_type", "confidence": "EXTRACTED", "source_file": "backend/api/v1/assets.py", "source_location": "L484", "weight": 1.0}, {"source": "v1_assets_probe_provider_config", "target": "user", "relation": "references", "context": "parameter_type", "confidence": "EXTRACTED", "source_file": "backend/api/v1/assets.py", "source_location": "L484", "weight": 1.0}, {"source": "users_ea_enel_documents_00_my_librefolio_librefolio_devwiki_corpus_backend_api_v1_assets_py", "target": "v1_assets_assign_providers_bulk", "relation": "contains", "confidence": "EXTRACTED", "source_file": "backend/api/v1/assets.py", "source_location": "L516", "weight": 1.0}, {"source": "v1_assets_assign_providers_bulk", "target": "faproviderassignmentitem", "relation": "references", "context": "generic_arg", "confidence": "EXTRACTED", "source_file": "backend/api/v1/assets.py", "source_location": "L516", "weight": 1.0}, {"source": "v1_assets_assign_providers_bulk", "target": "asyncsession", "relation": "references", "context": "parameter_type", "confidence": "EXTRACTED", "source_file": "backend/api/v1/assets.py", "source_location": "L516", "weight": 1.0}, {"source": "v1_assets_assign_providers_bulk", "target": "user", "relation": "references", "context": "parameter_type", "confidence": "EXTRACTED", "source_file": "backend/api/v1/assets.py", "source_location": "L516", "weight": 1.0}, {"source": "users_ea_enel_documents_00_my_librefolio_librefolio_devwiki_corpus_backend_api_v1_assets_py", "target": "v1_assets_remove_providers_bulk", "relation": "contains", "confidence": "EXTRACTED", "source_file": "backend/api/v1/assets.py", "source_location": "L532", "weight": 1.0}, {"source": "v1_assets_remove_providers_bulk", "target": "asyncsession", "relation": "references", "context": "parameter_type", "confidence": "EXTRACTED", "source_file": "backend/api/v1/assets.py", "source_location": "L532", "weight": 1.0}, {"source": "v1_assets_remove_providers_bulk", "target": "user", "relation": "references", "context": "parameter_type", "confidence": "EXTRACTED", "source_file": "backend/api/v1/assets.py", "source_location": "L532", "weight": 1.0}, {"source": "users_ea_enel_documents_00_my_librefolio_librefolio_devwiki_corpus_backend_api_v1_assets_py", "target": "v1_assets_get_provider_assignments", "relation": "contains", "confidence": "EXTRACTED", "source_file": "backend/api/v1/assets.py", "source_location": "L546", "weight": 1.0}, {"source": "v1_assets_get_provider_assignments", "target": "asyncsession", "relation": "references", "context": "parameter_type", "confidence": "EXTRACTED", "source_file": "backend/api/v1/assets.py", "source_location": "L546", "weight": 1.0}, {"source": "v1_assets_get_provider_assignments", "target": "user", "relation": "references", "context": "parameter_type", "confidence": "EXTRACTED", "source_file": "backend/api/v1/assets.py", "source_location": "L546", "weight": 1.0}, {"source": "users_ea_enel_documents_00_my_librefolio_librefolio_devwiki_corpus_backend_api_v1_assets_py", "target": "v1_assets_upsert_prices_bulk", "relation": "contains", "confidence": "EXTRACTED", "source_file": "backend/api/v1/assets.py", "source_location": "L616", "weight": 1.0}, {"source": "v1_assets_upsert_prices_bulk", "target": "faupsert", "relation": "references", "context": "generic_arg", "confidence": "EXTRACTED", "source_file": "backend/api/v1/assets.py", "source_location": "L616", "weight": 1.0}, {"source": "v1_assets_upsert_prices_bulk", "target": "asyncsession", "relation": "references", "context": "parameter_type", "confidence": "EXTRACTED", "source_file": "backend/api/v1/assets.py", "source_location": "L616", "weight": 1.0}, {"source": "v1_assets_upsert_prices_bulk", "target": "user", "relation": "references", "context": "parameter_type", "confidence": "EXTRACTED", "source_file": "backend/api/v1/assets.py", "source_location": "L616", "weight": 1.0}, {"source": "users_ea_enel_documents_00_my_librefolio_librefolio_devwiki_corpus_backend_api_v1_assets_py", "target": "v1_assets_delete_prices_bulk", "relation": "contains", "confidence": "EXTRACTED", "source_file": "backend/api/v1/assets.py", "source_location": "L646", "weight": 1.0}, {"source": "v1_assets_delete_prices_bulk", "target": "faassetdelete", "relation": "references", "context": "generic_arg", "confidence": "EXTRACTED", "source_file": "backend/api/v1/assets.py", "source_location": "L646", "weight": 1.0}, {"source": "v1_assets_delete_prices_bulk", "target": "asyncsession", "relation": "references", "context": "parameter_type", "confidence": "EXTRACTED", "source_file": "backend/api/v1/assets.py", "source_location": "L646", "weight": 1.0}, {"source": "v1_assets_delete_prices_bulk", "target": "user", "relation": "references", "context": "parameter_type", "confidence": "EXTRACTED", "source_file": "backend/api/v1/assets.py", "source_location": "L646", "weight": 1.0}, {"source": "users_ea_enel_documents_00_my_librefolio_librefolio_devwiki_corpus_backend_api_v1_assets_py", "target": "v1_assets_query_prices_bulk", "relation": "contains", "confidence": "EXTRACTED", "source_file": "backend/api/v1/assets.py", "source_location": "L672", "weight": 1.0}, {"source": "v1_assets_query_prices_bulk", "target": "fapricequeryitem", "relation": "references", "context": "generic_arg", "confidence": "EXTRACTED", "source_file": "backend/api/v1/assets.py", "source_location": "L672", "weight": 1.0}, {"source": "v1_assets_query_prices_bulk", "target": "asyncsession", "relation": "references", "context": "parameter_type", "confidence": "EXTRACTED", "source_file": "backend/api/v1/assets.py", "source_location": "L672", "weight": 1.0}, {"source": "v1_assets_query_prices_bulk", "target": "user", "relation": "references", "context": "parameter_type", "confidence": "EXTRACTED", "source_file": "backend/api/v1/assets.py", "source_location": "L672", "weight": 1.0}, {"source": "users_ea_enel_documents_00_my_librefolio_librefolio_devwiki_corpus_backend_api_v1_assets_py", "target": "v1_assets_get_current_prices_bulk", "relation": "contains", "confidence": "EXTRACTED", "source_file": "backend/api/v1/assets.py", "source_location": "L692", "weight": 1.0}, {"source": "v1_assets_get_current_prices_bulk", "target": "asyncsession", "relation": "references", "context": "parameter_type", "confidence": "EXTRACTED", "source_file": "backend/api/v1/assets.py", "source_location": "L692", "weight": 1.0}, {"source": "v1_assets_get_current_prices_bulk", "target": "user", "relation": "references", "context": "parameter_type", "confidence": "EXTRACTED", "source_file": "backend/api/v1/assets.py", "source_location": "L692", "weight": 1.0}, {"source": "users_ea_enel_documents_00_my_librefolio_librefolio_devwiki_corpus_backend_api_v1_assets_py", "target": "v1_assets_read_assets_bulk", "relation": "contains", "confidence": "EXTRACTED", "source_file": "backend/api/v1/assets.py", "source_location": "L737", "weight": 1.0}, {"source": "v1_assets_read_assets_bulk", "target": "asyncsession", "relation": "references", "context": "parameter_type", "confidence": "EXTRACTED", "source_file": "backend/api/v1/assets.py", "source_location": "L737", "weight": 1.0}, {"source": "v1_assets_read_assets_bulk", "target": "user", "relation": "references", "context": "parameter_type", "confidence": "EXTRACTED", "source_file": "backend/api/v1/assets.py", "source_location": "L737", "weight": 1.0}, {"source": "users_ea_enel_documents_00_my_librefolio_librefolio_devwiki_corpus_backend_api_v1_assets_py", "target": "v1_assets_sync_prices_bulk", "relation": "contains", "confidence": "EXTRACTED", "source_file": "backend/api/v1/assets.py", "source_location": "L865", "weight": 1.0}, {"source": "v1_assets_sync_prices_bulk", "target": "farefreshitem", "relation": "references", "context": "generic_arg", "confidence": "EXTRACTED", "source_file": "backend/api/v1/assets.py", "source_location": "L865", "weight": 1.0}, {"source": "v1_assets_sync_prices_bulk", "target": "asyncsession", "relation": "references", "context": "parameter_type", "confidence": "EXTRACTED", "source_file": "backend/api/v1/assets.py", "source_location": "L865", "weight": 1.0}, {"source": "v1_assets_sync_prices_bulk", "target": "user", "relation": "references", "context": "parameter_type", "confidence": "EXTRACTED", "source_file": "backend/api/v1/assets.py", "source_location": "L865", "weight": 1.0}, {"source": "users_ea_enel_documents_00_my_librefolio_librefolio_devwiki_corpus_backend_api_v1_assets_py", "target": "v1_assets_refresh_assets_from_provider", "relation": "contains", "confidence": "EXTRACTED", "source_file": "backend/api/v1/assets.py", "source_location": "L879", "weight": 1.0}, {"source": "v1_assets_refresh_assets_from_provider", "target": "asyncsession", "relation": "references", "context": "parameter_type", "confidence": "EXTRACTED", "source_file": "backend/api/v1/assets.py", "source_location": "L879", "weight": 1.0}, {"source": "v1_assets_refresh_assets_from_provider", "target": "user", "relation": "references", "context": "parameter_type", "confidence": "EXTRACTED", "source_file": "backend/api/v1/assets.py", "source_location": "L879", "weight": 1.0}, {"source": "users_ea_enel_documents_00_my_librefolio_librefolio_devwiki_corpus_backend_api_v1_assets_py", "target": "v1_assets_upsert_events_bulk", "relation": "contains", "confidence": "EXTRACTED", "source_file": "backend/api/v1/assets.py", "source_location": "L954", "weight": 1.0}, {"source": "v1_assets_upsert_events_bulk", "target": "faeventupsert", "relation": "references", "context": "generic_arg", "confidence": "EXTRACTED", "source_file": "backend/api/v1/assets.py", "source_location": "L954", "weight": 1.0}, {"source": "v1_assets_upsert_events_bulk", "target": "asyncsession", "relation": "references", "context": "parameter_type", "confidence": "EXTRACTED", "source_file": "backend/api/v1/assets.py", "source_location": "L954", "weight": 1.0}, {"source": "v1_assets_upsert_events_bulk", "target": "user", "relation": "references", "context": "parameter_type", "confidence": "EXTRACTED", "source_file": "backend/api/v1/assets.py", "source_location": "L954", "weight": 1.0}, {"source": "users_ea_enel_documents_00_my_librefolio_librefolio_devwiki_corpus_backend_api_v1_assets_py", "target": "v1_assets_delete_events_bulk", "relation": "contains", "confidence": "EXTRACTED", "source_file": "backend/api/v1/assets.py", "source_location": "L985", "weight": 1.0}, {"source": "v1_assets_delete_events_bulk", "target": "asyncsession", "relation": "references", "context": "parameter_type", "confidence": "EXTRACTED", "source_file": "backend/api/v1/assets.py", "source_location": "L985", "weight": 1.0}, {"source": "v1_assets_delete_events_bulk", "target": "user", "relation": "references", "context": "parameter_type", "confidence": "EXTRACTED", "source_file": "backend/api/v1/assets.py", "source_location": "L985", "weight": 1.0}, {"source": "users_ea_enel_documents_00_my_librefolio_librefolio_devwiki_corpus_backend_api_v1_assets_py", "target": "v1_assets_query_events_bulk", "relation": "contains", "confidence": "EXTRACTED", "source_file": "backend/api/v1/assets.py", "source_location": "L1010", "weight": 1.0}, {"source": "v1_assets_query_events_bulk", "target": "faeventqueryitem", "relation": "references", "context": "generic_arg", "confidence": "EXTRACTED", "source_file": "backend/api/v1/assets.py", "source_location": "L1010", "weight": 1.0}, {"source": "v1_assets_query_events_bulk", "target": "asyncsession", "relation": "references", "context": "parameter_type", "confidence": "EXTRACTED", "source_file": "backend/api/v1/assets.py", "source_location": "L1010", "weight": 1.0}, {"source": "v1_assets_query_events_bulk", "target": "user", "relation": "references", "context": "parameter_type", "confidence": "EXTRACTED", "source_file": "backend/api/v1/assets.py", "source_location": "L1010", "weight": 1.0}, {"source": "users_ea_enel_documents_00_my_librefolio_librefolio_devwiki_corpus_backend_api_v1_assets_py", "target": "v1_assets_get_events_by_ids", "relation": "contains", "confidence": "EXTRACTED", "source_file": "backend/api/v1/assets.py", "source_location": "L1028", "weight": 1.0}, {"source": "v1_assets_get_events_by_ids", "target": "asyncsession", "relation": "references", "context": "parameter_type", "confidence": "EXTRACTED", "source_file": "backend/api/v1/assets.py", "source_location": "L1028", "weight": 1.0}, {"source": "v1_assets_get_events_by_ids", "target": "user", "relation": "references", "context": "parameter_type", "confidence": "EXTRACTED", "source_file": "backend/api/v1/assets.py", "source_location": "L1028", "weight": 1.0}, {"source": "users_ea_enel_documents_00_my_librefolio_librefolio_devwiki_corpus_backend_api_v1_assets_py", "target": "v1_assets_market_data_summary", "relation": "contains", "confidence": "EXTRACTED", "source_file": "backend/api/v1/assets.py", "source_location": "L1082", "weight": 1.0}, {"source": "v1_assets_market_data_summary", "target": "asyncsession", "relation": "references", "context": "parameter_type", "confidence": "EXTRACTED", "source_file": "backend/api/v1/assets.py", "source_location": "L1082", "weight": 1.0}, {"source": "v1_assets_market_data_summary", "target": "user", "relation": "references", "context": "parameter_type", "confidence": "EXTRACTED", "source_file": "backend/api/v1/assets.py", "source_location": "L1082", "weight": 1.0}, {"source": "users_ea_enel_documents_00_my_librefolio_librefolio_devwiki_corpus_backend_api_v1_assets_py", "target": "v1_assets_wipe_market_data", "relation": "contains", "confidence": "EXTRACTED", "source_file": "backend/api/v1/assets.py", "source_location": "L1105", "weight": 1.0}, {"source": "v1_assets_wipe_market_data", "target": "asyncsession", "relation": "references", "context": "parameter_type", "confidence": "EXTRACTED", "source_file": "backend/api/v1/assets.py", "source_location": "L1105", "weight": 1.0}, {"source": "v1_assets_wipe_market_data", "target": "user", "relation": "references", "context": "parameter_type", "confidence": "EXTRACTED", "source_file": "backend/api/v1/assets.py", "source_location": "L1105", "weight": 1.0}, {"source": "v1_assets_get_all_assets", "target": "v1_assets_list_assets", "relation": "calls", "context": "call", "confidence": "EXTRACTED", "source_file": "backend/api/v1/assets.py", "source_location": "L214", "weight": 1.0}, {"source": "v1_assets_rationale_1", "target": "users_ea_enel_documents_00_my_librefolio_librefolio_devwiki_corpus_backend_api_v1_assets_py", "relation": "rationale_for", "confidence": "EXTRACTED", "source_file": "backend/api/v1/assets.py", "source_location": "L1", "weight": 1.0}, {"source": "v1_assets_rationale_89", "target": "v1_assets_create_assets_bulk", "relation": "rationale_for", "confidence": "EXTRACTED", "source_file": "backend/api/v1/assets.py", "source_location": "L89", "weight": 1.0}, {"source": "v1_assets_rationale_140", "target": "v1_assets_patch_assets_bulk", "relation": "rationale_for", "confidence": "EXTRACTED", "source_file": "backend/api/v1/assets.py", "source_location": "L140", "weight": 1.0}, {"source": "v1_assets_rationale_202", "target": "v1_assets_get_all_assets", "relation": "rationale_for", "confidence": "EXTRACTED", "source_file": "backend/api/v1/assets.py", "source_location": "L202", "weight": 1.0}, {"source": "v1_assets_rationale_237", "target": "v1_assets_list_assets", "relation": "rationale_for", "confidence": "EXTRACTED", "source_file": "backend/api/v1/assets.py", "source_location": "L237", "weight": 1.0}, {"source": "v1_assets_rationale_294", "target": "v1_assets_delete_assets_bulk", "relation": "rationale_for", "confidence": "EXTRACTED", "source_file": "backend/api/v1/assets.py", "source_location": "L294", "weight": 1.0}, {"source": "v1_assets_rationale_345", "target": "v1_assets_list_providers", "relation": "rationale_for", "confidence": "EXTRACTED", "source_file": "backend/api/v1/assets.py", "source_location": "L345", "weight": 1.0}, {"source": "v1_assets_rationale_397", "target": "v1_assets_search_assets_via_providers", "relation": "rationale_for", "confidence": "EXTRACTED", "source_file": "backend/api/v1/assets.py", "source_location": "L397", "weight": 1.0}, {"source": "v1_assets_rationale_456", "target": "v1_assets_search_assets_stream", "relation": "rationale_for", "confidence": "EXTRACTED", "source_file": "backend/api/v1/assets.py", "source_location": "L456", "weight": 1.0}, {"source": "v1_assets_rationale_521", "target": "v1_assets_assign_providers_bulk", "relation": "rationale_for", "confidence": "EXTRACTED", "source_file": "backend/api/v1/assets.py", "source_location": "L521", "weight": 1.0}, {"source": "v1_assets_rationale_537", "target": "v1_assets_remove_providers_bulk", "relation": "rationale_for", "confidence": "EXTRACTED", "source_file": "backend/api/v1/assets.py", "source_location": "L537", "weight": 1.0}, {"source": "v1_assets_rationale_551", "target": "v1_assets_get_provider_assignments", "relation": "rationale_for", "confidence": "EXTRACTED", "source_file": "backend/api/v1/assets.py", "source_location": "L551", "weight": 1.0}, {"source": "v1_assets_rationale_621", "target": "v1_assets_upsert_prices_bulk", "relation": "rationale_for", "confidence": "EXTRACTED", "source_file": "backend/api/v1/assets.py", "source_location": "L621", "weight": 1.0}, {"source": "v1_assets_rationale_651", "target": "v1_assets_delete_prices_bulk", "relation": "rationale_for", "confidence": "EXTRACTED", "source_file": "backend/api/v1/assets.py", "source_location": "L651", "weight": 1.0}, {"source": "v1_assets_rationale_677", "target": "v1_assets_query_prices_bulk", "relation": "rationale_for", "confidence": "EXTRACTED", "source_file": "backend/api/v1/assets.py", "source_location": "L677", "weight": 1.0}, {"source": "v1_assets_rationale_697", "target": "v1_assets_get_current_prices_bulk", "relation": "rationale_for", "confidence": "EXTRACTED", "source_file": "backend/api/v1/assets.py", "source_location": "L697", "weight": 1.0}, {"source": "v1_assets_rationale_742", "target": "v1_assets_read_assets_bulk", "relation": "rationale_for", "confidence": "EXTRACTED", "source_file": "backend/api/v1/assets.py", "source_location": "L742", "weight": 1.0}, {"source": "v1_assets_rationale_870", "target": "v1_assets_sync_prices_bulk", "relation": "rationale_for", "confidence": "EXTRACTED", "source_file": "backend/api/v1/assets.py", "source_location": "L870", "weight": 1.0}, {"source": "v1_assets_rationale_884", "target": "v1_assets_refresh_assets_from_provider", "relation": "rationale_for", "confidence": "EXTRACTED", "source_file": "backend/api/v1/assets.py", "source_location": "L884", "weight": 1.0}, {"source": "v1_assets_rationale_959", "target": "v1_assets_upsert_events_bulk", "relation": "rationale_for", "confidence": "EXTRACTED", "source_file": "backend/api/v1/assets.py", "source_location": "L959", "weight": 1.0}, {"source": "v1_assets_rationale_990", "target": "v1_assets_delete_events_bulk", "relation": "rationale_for", "confidence": "EXTRACTED", "source_file": "backend/api/v1/assets.py", "source_location": "L990", "weight": 1.0}, {"source": "v1_assets_rationale_1015", "target": "v1_assets_query_events_bulk", "relation": "rationale_for", "confidence": "EXTRACTED", "source_file": "backend/api/v1/assets.py", "source_location": "L1015", "weight": 1.0}, {"source": "v1_assets_rationale_1033", "target": "v1_assets_get_events_by_ids", "relation": "rationale_for", "confidence": "EXTRACTED", "source_file": "backend/api/v1/assets.py", "source_location": "L1033", "weight": 1.0}, {"source": "v1_assets_rationale_1087", "target": "v1_assets_market_data_summary", "relation": "rationale_for", "confidence": "EXTRACTED", "source_file": "backend/api/v1/assets.py", "source_location": "L1087", "weight": 1.0}, {"source": "v1_assets_rationale_1110", "target": "v1_assets_wipe_market_data", "relation": "rationale_for", "confidence": "EXTRACTED", "source_file": "backend/api/v1/assets.py", "source_location": "L1110", "weight": 1.0}], "raw_calls": [{"caller_nid": "v1_assets_create_assets_bulk", "callee": "error", "is_member_call": true, "source_file": "/Users/ea_enel/Documents/00_My/LibreFolio/LibreFolio_devWiki/corpus/backend/api/v1/assets.py", "source_location": "L130", "receiver": null}, {"caller_nid": "v1_assets_create_assets_bulk", "callee": "HTTPException", "is_member_call": false, "source_file": "/Users/ea_enel/Documents/00_My/LibreFolio/LibreFolio_devWiki/corpus/backend/api/v1/assets.py", "source_location": "L131", "receiver": null}, {"caller_nid": "v1_assets_patch_assets_bulk", "callee": "HTTPException", "is_member_call": false, "source_file": "/Users/ea_enel/Documents/00_My/LibreFolio/LibreFolio_devWiki/corpus/backend/api/v1/assets.py", "source_location": "L184", "receiver": null}, {"caller_nid": "v1_assets_patch_assets_bulk", "callee": "model_dump", "is_member_call": true, "source_file": "/Users/ea_enel/Documents/00_My/LibreFolio/LibreFolio_devWiki/corpus/backend/api/v1/assets.py", "source_location": "L189", "receiver": null}, {"caller_nid": "v1_assets_patch_assets_bulk", "callee": "error", "is_member_call": true, "source_file": "/Users/ea_enel/Documents/00_My/LibreFolio/LibreFolio_devWiki/corpus/backend/api/v1/assets.py", "source_location": "L196", "receiver": null}, {"caller_nid": "v1_assets_patch_assets_bulk", "callee": "HTTPException", "is_member_call": false, "source_file": "/Users/ea_enel/Documents/00_My/LibreFolio/LibreFolio_devWiki/corpus/backend/api/v1/assets.py", "source_location": "L197", "receiver": null}, {"caller_nid": "v1_assets_get_all_assets", "callee": "FAAinfoFiltersRequest", "is_member_call": false, "source_file": "/Users/ea_enel/Documents/00_My/LibreFolio/LibreFolio_devWiki/corpus/backend/api/v1/assets.py", "source_location": "L213", "receiver": null}, {"caller_nid": "v1_assets_get_all_assets", "callee": "error", "is_member_call": true, "source_file": "/Users/ea_enel/Documents/00_My/LibreFolio/LibreFolio_devWiki/corpus/backend/api/v1/assets.py", "source_location": "L216", "receiver": null}, {"caller_nid": "v1_assets_get_all_assets", "callee": "HTTPException", "is_member_call": false, "source_file": "/Users/ea_enel/Documents/00_My/LibreFolio/LibreFolio_devWiki/corpus/backend/api/v1/assets.py", "source_location": "L217", "receiver": null}, {"caller_nid": "v1_assets_list_assets", "callee": "FAAinfoFiltersRequest", "is_member_call": false, "source_file": "/Users/ea_enel/Documents/00_My/LibreFolio/LibreFolio_devWiki/corpus/backend/api/v1/assets.py", "source_location": "L268", "receiver": null}, {"caller_nid": "v1_assets_list_assets", "callee": "error", "is_member_call": true, "source_file": "/Users/ea_enel/Documents/00_My/LibreFolio/LibreFolio_devWiki/corpus/backend/api/v1/assets.py", "source_location": "L284", "receiver": null}, {"caller_nid": "v1_assets_list_assets", "callee": "HTTPException", "is_member_call": false, "source_file": "/Users/ea_enel/Documents/00_My/LibreFolio/LibreFolio_devWiki/corpus/backend/api/v1/assets.py", "source_location": "L285", "receiver": null}, {"caller_nid": "v1_assets_delete_assets_bulk", "callee": "error", "is_member_call": true, "source_file": "/Users/ea_enel/Documents/00_My/LibreFolio/LibreFolio_devWiki/corpus/backend/api/v1/assets.py", "source_location": "L331", "receiver": null}, {"caller_nid": "v1_assets_delete_assets_bulk", "callee": "HTTPException", "is_member_call": false, "source_file": "/Users/ea_enel/Documents/00_My/LibreFolio/LibreFolio_devWiki/corpus/backend/api/v1/assets.py", "source_location": "L332", "receiver": null}, {"caller_nid": "v1_assets_list_providers", "callee": "strip", "is_member_call": true, "source_file": "/Users/ea_enel/Documents/00_My/LibreFolio/LibreFolio_devWiki/corpus/backend/api/v1/assets.py", "source_location": "L352", "receiver": null}, {"caller_nid": "v1_assets_list_providers", "callee": "split", "is_member_call": true, "source_file": "/Users/ea_enel/Documents/00_My/LibreFolio/LibreFolio_devWiki/corpus/backend/api/v1/assets.py", "source_location": "L352", "receiver": null}, {"caller_nid": "v1_assets_list_providers", "callee": "strip", "is_member_call": true, "source_file": "/Users/ea_enel/Documents/00_My/LibreFolio/LibreFolio_devWiki/corpus/backend/api/v1/assets.py", "source_location": "L352", "receiver": null}, {"caller_nid": "v1_assets_list_providers", "callee": "get_provider_instance", "is_member_call": true, "source_file": "/Users/ea_enel/Documents/00_My/LibreFolio/LibreFolio_devWiki/corpus/backend/api/v1/assets.py", "source_location": "L366", "receiver": null}, {"caller_nid": "v1_assets_list_providers", "callee": "FAProviderParamField", "is_member_call": false, "source_file": "/Users/ea_enel/Documents/00_My/LibreFolio/LibreFolio_devWiki/corpus/backend/api/v1/assets.py", "source_location": "L372", "receiver": null}, {"caller_nid": "v1_assets_list_providers", "callee": "append", "is_member_call": true, "source_file": "/Users/ea_enel/Documents/00_My/LibreFolio/LibreFolio_devWiki/corpus/backend/api/v1/assets.py", "source_location": "L374", "receiver": null}, {"caller_nid": "v1_assets_list_providers", "callee": "FAProviderInfo", "is_member_call": false, "source_file": "/Users/ea_enel/Documents/00_My/LibreFolio/LibreFolio_devWiki/corpus/backend/api/v1/assets.py", "source_location": "L375", "receiver": null}, {"caller_nid": "v1_assets_search_assets_via_providers", "callee": "strip", "is_member_call": true, "source_file": "/Users/ea_enel/Documents/00_My/LibreFolio/LibreFolio_devWiki/corpus/backend/api/v1/assets.py", "source_location": "L444", "receiver": null}, {"caller_nid": "v1_assets_search_assets_via_providers", "callee": "split", "is_member_call": true, "source_file": "/Users/ea_enel/Documents/00_My/LibreFolio/LibreFolio_devWiki/corpus/backend/api/v1/assets.py", "source_location": "L444", "receiver": null}, {"caller_nid": "v1_assets_search_assets_via_providers", "callee": "strip", "is_member_call": true, "source_file": "/Users/ea_enel/Documents/00_My/LibreFolio/LibreFolio_devWiki/corpus/backend/api/v1/assets.py", "source_location": "L444", "receiver": null}, {"caller_nid": "v1_assets_search_assets_via_providers", "callee": "search", "is_member_call": true, "source_file": "/Users/ea_enel/Documents/00_My/LibreFolio/LibreFolio_devWiki/corpus/backend/api/v1/assets.py", "source_location": "L447", "receiver": null}, {"caller_nid": "v1_assets_search_assets_stream", "callee": "strip", "is_member_call": true, "source_file": "/Users/ea_enel/Documents/00_My/LibreFolio/LibreFolio_devWiki/corpus/backend/api/v1/assets.py", "source_location": "L470", "receiver": null}, {"caller_nid": "v1_assets_search_assets_stream", "callee": "split", "is_member_call": true, "source_file": "/Users/ea_enel/Documents/00_My/LibreFolio/LibreFolio_devWiki/corpus/backend/api/v1/assets.py", "source_location": "L470", "receiver": null}, {"caller_nid": "v1_assets_search_assets_stream", "callee": "strip", "is_member_call": true, "source_file": "/Users/ea_enel/Documents/00_My/LibreFolio/LibreFolio_devWiki/corpus/backend/api/v1/assets.py", "source_location": "L470", "receiver": null}, {"caller_nid": "v1_assets_search_assets_stream", "callee": "StreamingResponse", "is_member_call": false, "source_file": "/Users/ea_enel/Documents/00_My/LibreFolio/LibreFolio_devWiki/corpus/backend/api/v1/assets.py", "source_location": "L472", "receiver": null}, {"caller_nid": "v1_assets_search_assets_stream", "callee": "search_stream", "is_member_call": true, "source_file": "/Users/ea_enel/Documents/00_My/LibreFolio/LibreFolio_devWiki/corpus/backend/api/v1/assets.py", "source_location": "L473", "receiver": null}, {"caller_nid": "v1_assets_probe_provider_config", "callee": "format", "is_member_call": true, "source_file": "/Users/ea_enel/Documents/00_My/LibreFolio/LibreFolio_devWiki/corpus/backend/api/v1/assets.py", "source_location": "L488", "receiver": null}, {"caller_nid": "v1_assets_probe_provider_config", "callee": "join", "is_member_call": true, "source_file": "/Users/ea_enel/Documents/00_My/LibreFolio/LibreFolio_devWiki/corpus/backend/api/v1/assets.py", "source_location": "L501", "receiver": null}, {"caller_nid": "v1_assets_probe_provider_config", "callee": "HTTPException", "is_member_call": false, "source_file": "/Users/ea_enel/Documents/00_My/LibreFolio/LibreFolio_devWiki/corpus/backend/api/v1/assets.py", "source_location": "L510", "receiver": null}, {"caller_nid": "v1_assets_probe_provider_config", "callee": "HTTPException", "is_member_call": false, "source_file": "/Users/ea_enel/Documents/00_My/LibreFolio/LibreFolio_devWiki/corpus/backend/api/v1/assets.py", "source_location": "L512", "receiver": null}, {"caller_nid": "v1_assets_assign_providers_bulk", "callee": "bulk_assign_providers", "is_member_call": true, "source_file": "/Users/ea_enel/Documents/00_My/LibreFolio/LibreFolio_devWiki/corpus/backend/api/v1/assets.py", "source_location": "L523", "receiver": null}, {"caller_nid": "v1_assets_assign_providers_bulk", "callee": "FABulkAssignResponse", "is_member_call": false, "source_file": "/Users/ea_enel/Documents/00_My/LibreFolio/LibreFolio_devWiki/corpus/backend/api/v1/assets.py", "source_location": "L525", "receiver": null}, {"caller_nid": "v1_assets_assign_providers_bulk", "callee": "error", "is_member_call": true, "source_file": "/Users/ea_enel/Documents/00_My/LibreFolio/LibreFolio_devWiki/corpus/backend/api/v1/assets.py", "source_location": "L527", "receiver": null}, {"caller_nid": "v1_assets_assign_providers_bulk", "callee": "HTTPException", "is_member_call": false, "source_file": "/Users/ea_enel/Documents/00_My/LibreFolio/LibreFolio_devWiki/corpus/backend/api/v1/assets.py", "source_location": "L528", "receiver": null}, {"caller_nid": "v1_assets_remove_providers_bulk", "callee": "bulk_remove_providers", "is_member_call": true, "source_file": "/Users/ea_enel/Documents/00_My/LibreFolio/LibreFolio_devWiki/corpus/backend/api/v1/assets.py", "source_location": "L539", "receiver": null}, {"caller_nid": "v1_assets_remove_providers_bulk", "callee": "error", "is_member_call": true, "source_file": "/Users/ea_enel/Documents/00_My/LibreFolio/LibreFolio_devWiki/corpus/backend/api/v1/assets.py", "source_location": "L541", "receiver": null}, {"caller_nid": "v1_assets_remove_providers_bulk", "callee": "HTTPException", "is_member_call": false, "source_file": "/Users/ea_enel/Documents/00_My/LibreFolio/LibreFolio_devWiki/corpus/backend/api/v1/assets.py", "source_location": "L542", "receiver": null}, {"caller_nid": "v1_assets_get_provider_assignments", "callee": "where", "is_member_call": true, "source_file": "/Users/ea_enel/Documents/00_My/LibreFolio/LibreFolio_devWiki/corpus/backend/api/v1/assets.py", "source_location": "L577", "receiver": null}, {"caller_nid": "v1_assets_get_provider_assignments", "callee": "select", "is_member_call": false, "source_file": "/Users/ea_enel/Documents/00_My/LibreFolio/LibreFolio_devWiki/corpus/backend/api/v1/assets.py", "source_location": "L577", "receiver": null}, {"caller_nid": "v1_assets_get_provider_assignments", "callee": "in_", "is_member_call": true, "source_file": "/Users/ea_enel/Documents/00_My/LibreFolio/LibreFolio_devWiki/corpus/backend/api/v1/assets.py", "source_location": "L577", "receiver": null}, {"caller_nid": "v1_assets_get_provider_assignments", "callee": "execute", "is_member_call": true, "source_file": "/Users/ea_enel/Documents/00_My/LibreFolio/LibreFolio_devWiki/corpus/backend/api/v1/assets.py", "source_location": "L578", "receiver": null}, {"caller_nid": "v1_assets_get_provider_assignments", "callee": "scalars", "is_member_call": true, "source_file": "/Users/ea_enel/Documents/00_My/LibreFolio/LibreFolio_devWiki/corpus/backend/api/v1/assets.py", "source_location": "L579", "receiver": null}, {"caller_nid": "v1_assets_get_provider_assignments", "callee": "loads", "is_member_call": true, "source_file": "/Users/ea_enel/Documents/00_My/LibreFolio/LibreFolio_devWiki/corpus/backend/api/v1/assets.py", "source_location": "L584", "receiver": null}, {"caller_nid": "v1_assets_get_provider_assignments", "callee": "get_provider_instance", "is_member_call": true, "source_file": "/Users/ea_enel/Documents/00_My/LibreFolio/LibreFolio_devWiki/corpus/backend/api/v1/assets.py", "source_location": "L588", "receiver": null}, {"caller_nid": "v1_assets_get_provider_assignments", "callee": "get_asset_url", "is_member_call": true, "source_file": "/Users/ea_enel/Documents/00_My/LibreFolio/LibreFolio_devWiki/corpus/backend/api/v1/assets.py", "source_location": "L590", "receiver": null}, {"caller_nid": "v1_assets_get_provider_assignments", "callee": "append", "is_member_call": true, "source_file": "/Users/ea_enel/Documents/00_My/LibreFolio/LibreFolio_devWiki/corpus/backend/api/v1/assets.py", "source_location": "L592", "receiver": null}, {"caller_nid": "v1_assets_get_provider_assignments", "callee": "FAProviderAssignmentReadItem", "is_member_call": false, "source_file": "/Users/ea_enel/Documents/00_My/LibreFolio/LibreFolio_devWiki/corpus/backend/api/v1/assets.py", "source_location": "L593", "receiver": null}, {"caller_nid": "v1_assets_get_provider_assignments", "callee": "isoformat", "is_member_call": true, "source_file": "/Users/ea_enel/Documents/00_My/LibreFolio/LibreFolio_devWiki/corpus/backend/api/v1/assets.py", "source_location": "L599", "receiver": null}, {"caller_nid": "v1_assets_get_provider_assignments", "callee": "error", "is_member_call": true, "source_file": "/Users/ea_enel/Documents/00_My/LibreFolio/LibreFolio_devWiki/corpus/backend/api/v1/assets.py", "source_location": "L606", "receiver": null}, {"caller_nid": "v1_assets_get_provider_assignments", "callee": "HTTPException", "is_member_call": false, "source_file": "/Users/ea_enel/Documents/00_My/LibreFolio/LibreFolio_devWiki/corpus/backend/api/v1/assets.py", "source_location": "L607", "receiver": null}, {"caller_nid": "v1_assets_upsert_prices_bulk", "callee": "bulk_upsert_prices", "is_member_call": true, "source_file": "/Users/ea_enel/Documents/00_My/LibreFolio/LibreFolio_devWiki/corpus/backend/api/v1/assets.py", "source_location": "L624", "receiver": null}, {"caller_nid": "v1_assets_upsert_prices_bulk", "callee": "FAUpsertResult", "is_member_call": false, "source_file": "/Users/ea_enel/Documents/00_My/LibreFolio/LibreFolio_devWiki/corpus/backend/api/v1/assets.py", "source_location": "L626", "receiver": null}, {"caller_nid": "v1_assets_upsert_prices_bulk", "callee": "FABulkUpsertResponse", "is_member_call": false, "source_file": "/Users/ea_enel/Documents/00_My/LibreFolio/LibreFolio_devWiki/corpus/backend/api/v1/assets.py", "source_location": "L629", "receiver": null}, {"caller_nid": "v1_assets_upsert_prices_bulk", "callee": "warning", "is_member_call": true, "source_file": "/Users/ea_enel/Documents/00_My/LibreFolio/LibreFolio_devWiki/corpus/backend/api/v1/assets.py", "source_location": "L638", "receiver": null}, {"caller_nid": "v1_assets_upsert_prices_bulk", "callee": "HTTPException", "is_member_call": false, "source_file": "/Users/ea_enel/Documents/00_My/LibreFolio/LibreFolio_devWiki/corpus/backend/api/v1/assets.py", "source_location": "L639", "receiver": null}, {"caller_nid": "v1_assets_upsert_prices_bulk", "callee": "error", "is_member_call": true, "source_file": "/Users/ea_enel/Documents/00_My/LibreFolio/LibreFolio_devWiki/corpus/backend/api/v1/assets.py", "source_location": "L641", "receiver": null}, {"caller_nid": "v1_assets_upsert_prices_bulk", "callee": "HTTPException", "is_member_call": false, "source_file": "/Users/ea_enel/Documents/00_My/LibreFolio/LibreFolio_devWiki/corpus/backend/api/v1/assets.py", "source_location": "L642", "receiver": null}, {"caller_nid": "v1_assets_delete_prices_bulk", "callee": "bulk_delete_prices", "is_member_call": true, "source_file": "/Users/ea_enel/Documents/00_My/LibreFolio/LibreFolio_devWiki/corpus/backend/api/v1/assets.py", "source_location": "L653", "receiver": null}, {"caller_nid": "v1_assets_delete_prices_bulk", "callee": "error", "is_member_call": true, "source_file": "/Users/ea_enel/Documents/00_My/LibreFolio/LibreFolio_devWiki/corpus/backend/api/v1/assets.py", "source_location": "L655", "receiver": null}, {"caller_nid": "v1_assets_delete_prices_bulk", "callee": "HTTPException", "is_member_call": false, "source_file": "/Users/ea_enel/Documents/00_My/LibreFolio/LibreFolio_devWiki/corpus/backend/api/v1/assets.py", "source_location": "L656", "receiver": null}, {"caller_nid": "v1_assets_query_prices_bulk", "callee": "get_prices_bulk", "is_member_call": true, "source_file": "/Users/ea_enel/Documents/00_My/LibreFolio/LibreFolio_devWiki/corpus/backend/api/v1/assets.py", "source_location": "L684", "receiver": null}, {"caller_nid": "v1_assets_query_prices_bulk", "callee": "FAPriceQueryResponse", "is_member_call": false, "source_file": "/Users/ea_enel/Documents/00_My/LibreFolio/LibreFolio_devWiki/corpus/backend/api/v1/assets.py", "source_location": "L685", "receiver": null}, {"caller_nid": "v1_assets_query_prices_bulk", "callee": "error", "is_member_call": true, "source_file": "/Users/ea_enel/Documents/00_My/LibreFolio/LibreFolio_devWiki/corpus/backend/api/v1/assets.py", "source_location": "L687", "receiver": null}, {"caller_nid": "v1_assets_query_prices_bulk", "callee": "HTTPException", "is_member_call": false, "source_file": "/Users/ea_enel/Documents/00_My/LibreFolio/LibreFolio_devWiki/corpus/backend/api/v1/assets.py", "source_location": "L688", "receiver": null}, {"caller_nid": "v1_assets_get_current_prices_bulk", "callee": "FACurrentPriceResponse", "is_member_call": false, "source_file": "/Users/ea_enel/Documents/00_My/LibreFolio/LibreFolio_devWiki/corpus/backend/api/v1/assets.py", "source_location": "L729", "receiver": null}, {"caller_nid": "v1_assets_get_current_prices_bulk", "callee": "error", "is_member_call": true, "source_file": "/Users/ea_enel/Documents/00_My/LibreFolio/LibreFolio_devWiki/corpus/backend/api/v1/assets.py", "source_location": "L731", "receiver": null}, {"caller_nid": "v1_assets_get_current_prices_bulk", "callee": "HTTPException", "is_member_call": false, "source_file": "/Users/ea_enel/Documents/00_My/LibreFolio/LibreFolio_devWiki/corpus/backend/api/v1/assets.py", "source_location": "L732", "receiver": null}, {"caller_nid": "v1_assets_read_assets_bulk", "callee": "where", "is_member_call": true, "source_file": "/Users/ea_enel/Documents/00_My/LibreFolio/LibreFolio_devWiki/corpus/backend/api/v1/assets.py", "source_location": "L809", "receiver": null}, {"caller_nid": "v1_assets_read_assets_bulk", "callee": "select", "is_member_call": false, "source_file": "/Users/ea_enel/Documents/00_My/LibreFolio/LibreFolio_devWiki/corpus/backend/api/v1/assets.py", "source_location": "L809", "receiver": null}, {"caller_nid": "v1_assets_read_assets_bulk", "callee": "in_", "is_member_call": true, "source_file": "/Users/ea_enel/Documents/00_My/LibreFolio/LibreFolio_devWiki/corpus/backend/api/v1/assets.py", "source_location": "L809", "receiver": null}, {"caller_nid": "v1_assets_read_assets_bulk", "callee": "execute", "is_member_call": true, "source_file": "/Users/ea_enel/Documents/00_My/LibreFolio/LibreFolio_devWiki/corpus/backend/api/v1/assets.py", "source_location": "L810", "receiver": null}, {"caller_nid": "v1_assets_read_assets_bulk", "callee": "scalars", "is_member_call": true, "source_file": "/Users/ea_enel/Documents/00_My/LibreFolio/LibreFolio_devWiki/corpus/backend/api/v1/assets.py", "source_location": "L811", "receiver": null}, {"caller_nid": "v1_assets_read_assets_bulk", "callee": "where", "is_member_call": true, "source_file": "/Users/ea_enel/Documents/00_My/LibreFolio/LibreFolio_devWiki/corpus/backend/api/v1/assets.py", "source_location": "L815", "receiver": null}, {"caller_nid": "v1_assets_read_assets_bulk", "callee": "select", "is_member_call": false, "source_file": "/Users/ea_enel/Documents/00_My/LibreFolio/LibreFolio_devWiki/corpus/backend/api/v1/assets.py", "source_location": "L815", "receiver": null}, {"caller_nid": "v1_assets_read_assets_bulk", "callee": "in_", "is_member_call": true, "source_file": "/Users/ea_enel/Documents/00_My/LibreFolio/LibreFolio_devWiki/corpus/backend/api/v1/assets.py", "source_location": "L818", "receiver": null}, {"caller_nid": "v1_assets_read_assets_bulk", "callee": "execute", "is_member_call": true, "source_file": "/Users/ea_enel/Documents/00_My/LibreFolio/LibreFolio_devWiki/corpus/backend/api/v1/assets.py", "source_location": "L819", "receiver": null}, {"caller_nid": "v1_assets_read_assets_bulk", "callee": "fetchall", "is_member_call": true, "source_file": "/Users/ea_enel/Documents/00_My/LibreFolio/LibreFolio_devWiki/corpus/backend/api/v1/assets.py", "source_location": "L820", "receiver": null}, {"caller_nid": "v1_assets_read_assets_bulk", "callee": "get", "is_member_call": true, "source_file": "/Users/ea_enel/Documents/00_My/LibreFolio/LibreFolio_devWiki/corpus/backend/api/v1/assets.py", "source_location": "L824", "receiver": null}, {"caller_nid": "v1_assets_read_assets_bulk", "callee": "model_validate_json", "is_member_call": true, "source_file": "/Users/ea_enel/Documents/00_My/LibreFolio/LibreFolio_devWiki/corpus/backend/api/v1/assets.py", "source_location": "L832", "receiver": null}, {"caller_nid": "v1_assets_read_assets_bulk", "callee": "error", "is_member_call": true, "source_file": "/Users/ea_enel/Documents/00_My/LibreFolio/LibreFolio_devWiki/corpus/backend/api/v1/assets.py", "source_location": "L834", "receiver": null}, {"caller_nid": "v1_assets_read_assets_bulk", "callee": "append", "is_member_call": true, "source_file": "/Users/ea_enel/Documents/00_My/LibreFolio/LibreFolio_devWiki/corpus/backend/api/v1/assets.py", "source_location": "L840", "receiver": null}, {"caller_nid": "v1_assets_read_assets_bulk", "callee": "FAAssetMetadataResponse", "is_member_call": false, "source_file": "/Users/ea_enel/Documents/00_My/LibreFolio/LibreFolio_devWiki/corpus/backend/api/v1/assets.py", "source_location": "L841", "receiver": null}, {"caller_nid": "v1_assets_read_assets_bulk", "callee": "get", "is_member_call": true, "source_file": "/Users/ea_enel/Documents/00_My/LibreFolio/LibreFolio_devWiki/corpus/backend/api/v1/assets.py", "source_location": "L849", "receiver": null}, {"caller_nid": "v1_assets_read_assets_bulk", "callee": "error", "is_member_call": true, "source_file": "/Users/ea_enel/Documents/00_My/LibreFolio/LibreFolio_devWiki/corpus/backend/api/v1/assets.py", "source_location": "L855", "receiver": null}, {"caller_nid": "v1_assets_read_assets_bulk", "callee": "HTTPException", "is_member_call": false, "source_file": "/Users/ea_enel/Documents/00_My/LibreFolio/LibreFolio_devWiki/corpus/backend/api/v1/assets.py", "source_location": "L856", "receiver": null}, {"caller_nid": "v1_assets_sync_prices_bulk", "callee": "bulk_refresh_prices", "is_member_call": true, "source_file": "/Users/ea_enel/Documents/00_My/LibreFolio/LibreFolio_devWiki/corpus/backend/api/v1/assets.py", "source_location": "L872", "receiver": null}, {"caller_nid": "v1_assets_sync_prices_bulk", "callee": "error", "is_member_call": true, "source_file": "/Users/ea_enel/Documents/00_My/LibreFolio/LibreFolio_devWiki/corpus/backend/api/v1/assets.py", "source_location": "L874", "receiver": null}, {"caller_nid": "v1_assets_sync_prices_bulk", "callee": "HTTPException", "is_member_call": false, "source_file": "/Users/ea_enel/Documents/00_My/LibreFolio/LibreFolio_devWiki/corpus/backend/api/v1/assets.py", "source_location": "L875", "receiver": null}, {"caller_nid": "v1_assets_refresh_assets_from_provider", "callee": "error", "is_member_call": true, "source_file": "/Users/ea_enel/Documents/00_My/LibreFolio/LibreFolio_devWiki/corpus/backend/api/v1/assets.py", "source_location": "L944", "receiver": null}, {"caller_nid": "v1_assets_refresh_assets_from_provider", "callee": "HTTPException", "is_member_call": false, "source_file": "/Users/ea_enel/Documents/00_My/LibreFolio/LibreFolio_devWiki/corpus/backend/api/v1/assets.py", "source_location": "L945", "receiver": null}, {"caller_nid": "v1_assets_upsert_events_bulk", "callee": "bulk_upsert_events", "is_member_call": true, "source_file": "/Users/ea_enel/Documents/00_My/LibreFolio/LibreFolio_devWiki/corpus/backend/api/v1/assets.py", "source_location": "L969", "receiver": null}, {"caller_nid": "v1_assets_upsert_events_bulk", "callee": "FAEventUpsertResult", "is_member_call": false, "source_file": "/Users/ea_enel/Documents/00_My/LibreFolio/LibreFolio_devWiki/corpus/backend/api/v1/assets.py", "source_location": "L970", "receiver": null}, {"caller_nid": "v1_assets_upsert_events_bulk", "callee": "FABulkEventUpsertResponse", "is_member_call": false, "source_file": "/Users/ea_enel/Documents/00_My/LibreFolio/LibreFolio_devWiki/corpus/backend/api/v1/assets.py", "source_location": "L971", "receiver": null}, {"caller_nid": "v1_assets_upsert_events_bulk", "callee": "HTTPException", "is_member_call": false, "source_file": "/Users/ea_enel/Documents/00_My/LibreFolio/LibreFolio_devWiki/corpus/backend/api/v1/assets.py", "source_location": "L978", "receiver": null}, {"caller_nid": "v1_assets_upsert_events_bulk", "callee": "error", "is_member_call": true, "source_file": "/Users/ea_enel/Documents/00_My/LibreFolio/LibreFolio_devWiki/corpus/backend/api/v1/assets.py", "source_location": "L980", "receiver": null}, {"caller_nid": "v1_assets_upsert_events_bulk", "callee": "HTTPException", "is_member_call": false, "source_file": "/Users/ea_enel/Documents/00_My/LibreFolio/LibreFolio_devWiki/corpus/backend/api/v1/assets.py", "source_location": "L981", "receiver": null}, {"caller_nid": "v1_assets_delete_events_bulk", "callee": "error", "is_member_call": true, "source_file": "/Users/ea_enel/Documents/00_My/LibreFolio/LibreFolio_devWiki/corpus/backend/api/v1/assets.py", "source_location": "L1005", "receiver": null}, {"caller_nid": "v1_assets_delete_events_bulk", "callee": "HTTPException", "is_member_call": false, "source_file": "/Users/ea_enel/Documents/00_My/LibreFolio/LibreFolio_devWiki/corpus/backend/api/v1/assets.py", "source_location": "L1006", "receiver": null}, {"caller_nid": "v1_assets_query_events_bulk", "callee": "FAEventQueryResponse", "is_member_call": false, "source_file": "/Users/ea_enel/Documents/00_My/LibreFolio/LibreFolio_devWiki/corpus/backend/api/v1/assets.py", "source_location": "L1021", "receiver": null}, {"caller_nid": "v1_assets_query_events_bulk", "callee": "error", "is_member_call": true, "source_file": "/Users/ea_enel/Documents/00_My/LibreFolio/LibreFolio_devWiki/corpus/backend/api/v1/assets.py", "source_location": "L1023", "receiver": null}, {"caller_nid": "v1_assets_query_events_bulk", "callee": "HTTPException", "is_member_call": false, "source_file": "/Users/ea_enel/Documents/00_My/LibreFolio/LibreFolio_devWiki/corpus/backend/api/v1/assets.py", "source_location": "L1024", "receiver": null}, {"caller_nid": "v1_assets_get_events_by_ids", "callee": "FAEventQueryResponse", "is_member_call": false, "source_file": "/Users/ea_enel/Documents/00_My/LibreFolio/LibreFolio_devWiki/corpus/backend/api/v1/assets.py", "source_location": "L1070", "receiver": null}, {"caller_nid": "v1_assets_get_events_by_ids", "callee": "error", "is_member_call": true, "source_file": "/Users/ea_enel/Documents/00_My/LibreFolio/LibreFolio_devWiki/corpus/backend/api/v1/assets.py", "source_location": "L1072", "receiver": null}, {"caller_nid": "v1_assets_get_events_by_ids", "callee": "HTTPException", "is_member_call": false, "source_file": "/Users/ea_enel/Documents/00_My/LibreFolio/LibreFolio_devWiki/corpus/backend/api/v1/assets.py", "source_location": "L1073", "receiver": null}, {"caller_nid": "v1_assets_market_data_summary", "callee": "wipe_market_data_for_currency_change", "is_member_call": true, "source_file": "/Users/ea_enel/Documents/00_My/LibreFolio/LibreFolio_devWiki/corpus/backend/api/v1/assets.py", "source_location": "L1095", "receiver": null}, {"caller_nid": "v1_assets_market_data_summary", "callee": "HTTPException", "is_member_call": false, "source_file": "/Users/ea_enel/Documents/00_My/LibreFolio/LibreFolio_devWiki/corpus/backend/api/v1/assets.py", "source_location": "L1098", "receiver": null}, {"caller_nid": "v1_assets_market_data_summary", "callee": "error", "is_member_call": true, "source_file": "/Users/ea_enel/Documents/00_My/LibreFolio/LibreFolio_devWiki/corpus/backend/api/v1/assets.py", "source_location": "L1100", "receiver": null}, {"caller_nid": "v1_assets_market_data_summary", "callee": "HTTPException", "is_member_call": false, "source_file": "/Users/ea_enel/Documents/00_My/LibreFolio/LibreFolio_devWiki/corpus/backend/api/v1/assets.py", "source_location": "L1101", "receiver": null}, {"caller_nid": "v1_assets_wipe_market_data", "callee": "wipe_market_data_for_currency_change", "is_member_call": true, "source_file": "/Users/ea_enel/Documents/00_My/LibreFolio/LibreFolio_devWiki/corpus/backend/api/v1/assets.py", "source_location": "L1129", "receiver": null}, {"caller_nid": "v1_assets_wipe_market_data", "callee": "HTTPException", "is_member_call": false, "source_file": "/Users/ea_enel/Documents/00_My/LibreFolio/LibreFolio_devWiki/corpus/backend/api/v1/assets.py", "source_location": "L1132", "receiver": null}, {"caller_nid": "v1_assets_wipe_market_data", "callee": "error", "is_member_call": true, "source_file": "/Users/ea_enel/Documents/00_My/LibreFolio/LibreFolio_devWiki/corpus/backend/api/v1/assets.py", "source_location": "L1134", "receiver": null}, {"caller_nid": "v1_assets_wipe_market_data", "callee": "HTTPException", "is_member_call": false, "source_file": "/Users/ea_enel/Documents/00_My/LibreFolio/LibreFolio_devWiki/corpus/backend/api/v1/assets.py", "source_location": "L1135", "receiver": null}]}