{"nodes": [{"id": "provider_shutdown_generic", "label": "Generic Provider Shutdown Mechanism", "file_type": "rationale", "source_file": "wiki/decisions/provider-shutdown-generic.md", "source_location": null, "source_url": null, "captured_at": null, "author": null, "contributor": null}, {"id": "feature_f059", "label": "F-059 Provider Registry Pattern", "file_type": "document", "source_file": "wiki/decisions/provider-shutdown-generic.md", "source_location": null, "source_url": null, "captured_at": null, "author": null, "contributor": null}], "edges": [{"source": "provider_shutdown_generic", "target": "feature_f059", "relation": "references", "confidence": "EXTRACTED", "confidence_score": 1.0, "source_file": "wiki/decisions/provider-shutdown-generic.md", "source_location": null, "weight": 1.0}], "hyperedges": []}